codebraid/__init__.py
codebraid/cmdline.py
codebraid/code_chunks.py
codebraid/code_collections.py
codebraid/codebraid_defaults.py
codebraid/err.py
codebraid/fmtversion.py
codebraid/language.py
codebraid/message.py
codebraid/progress.py
codebraid/terminal.py
codebraid/util.py
codebraid/version.py
codebraid/codeprocessors/__init__.py
codebraid/codeprocessors/base.py
codebraid/codeprocessors/exec_builtin.py
codebraid/codeprocessors/exec_jupyter.py
codebraid/converters/__init__.py
codebraid/converters/base.py
codebraid/converters/pandoc.py
codebraid/languages/R.bespon
codebraid/languages/gap.bespon
codebraid/languages/index.bespon
codebraid/languages/javascript.bespon
codebraid/languages/julia.bespon
codebraid/languages/python.bespon
codebraid/languages/rust.bespon
codebraid/languages/shell.bespon
codebraid/languages/scripts/python_repl.py
codebraid-0.11.0.dist-info/CHANGELOG.md
codebraid-0.11.0.dist-info/LICENSE.txt
codebraid-0.11.0.dist-info/METADATA
codebraid-0.11.0.dist-info/PKG-INFO-GROOT
codebraid-0.11.0.dist-info/WHEEL
codebraid-0.11.0.dist-info/entry_points.txt
codebraid-0.11.0.dist-info/top_level.txt
codebraid-0.11.0.dist-info/RECORD
