Metadata-Version: 2.1
Name: codebraid
Version: 0.11.0
Summary: Live code in Pandoc Markdown
Author-email: "Geoffrey M. Poore" <gpoore@gmail.com>
License: BSD 3-Clause License
Project-URL: homepage, https://codebraid.org/
Project-URL: repository, http://github.com/gpoore/codebraid
Project-URL: changelog, https://github.com/gpoore/codebraid/blob/master/CHANGELOG.md
Keywords: dynamic documents,reproducible research,notebook,markdown,pandoc,LaTeX
Classifier: Development Status :: 4 - Beta
Classifier: Programming Language :: Python
Classifier: Environment :: Console
Classifier: Intended Audience :: Developers
Classifier: Intended Audience :: Education
Classifier: Intended Audience :: Science/Research
Classifier: License :: OSI Approved :: BSD License
Classifier: Operating System :: OS Independent
Classifier: Topic :: Documentation
Classifier: Topic :: Education
Classifier: Topic :: Software Development
Classifier: Topic :: Software Development :: Build Tools
Classifier: Topic :: Software Development :: Documentation
Classifier: Topic :: Text Processing
Classifier: Topic :: Text Processing :: Markup
Requires-Python: >=3.7
License-File: LICENSE.txt
License-File: CHANGELOG.md
Requires-Dist: bespon >=0.7.0
